LICENSE
MANIFEST.in
README.md
setup.py
SyntaxAutoFix/__init__.py
SyntaxAutoFix/__main__.py
SyntaxAutoFix/stats-gui.py
SyntaxAutoFix/syntaxautofix.py
SyntaxAutoFix.egg-info/PKG-INFO
SyntaxAutoFix.egg-info/SOURCES.txt
SyntaxAutoFix.egg-info/dependency_links.txt
SyntaxAutoFix.egg-info/entry_points.txt
SyntaxAutoFix.egg-info/requires.txt
SyntaxAutoFix.egg-info/top_level.txt
SyntaxAutoFix/utils/__init__.py
SyntaxAutoFix/utils/data_handlers.py
SyntaxAutoFix/words/en.json
SyntaxAutoFix/words/es.json
SyntaxAutoFix/words/fr.json
SyntaxAutoFix/words/it.json