Metadata-Version: 2.1
Name: SyntaxAutoFix
Version: 2.5.1
Summary: Autofix your typos on Linux easily!
Home-page: https://github.com/Mte90/SyntaxAutoFix
Author: Mte90
Author-email: mte90net@gmail.com
License: UNKNOWN
Platform: UNKNOWN
License-File: LICENSE
